{
  "ftp_leak": {
    "ip": "93.127.133.142",
    "port": 2121,
    "credentials": {
      "username": "jdupont",
      "password": "jdupont@2024!",
      "login_success": false
    },
    "timestamp": "2025-08-28T22:14:07Z"
  },
  "config_flags": {
    "debug_mode": true,
    "max_retries": 5,
    "logging": "verbose"
  },
  "internal_notes": [
    "Check failed logins on external FTP service",
    "Possible brute force attempt on port 2121",
    "User 'jdupont' not registered in LDAP"
  ],
  "uuid": "d5a2b1c8-4d87-11ee-be56-0242ac120002",
  "misc_data": {
    "hex_token": "4f6b89fa12e7ffcc003b1a9d",
    "deprecated_endpoints": [
      "/api/v1/legacy/auth",
      "/debug/ftp_test"
    ],
    "feature_flags": {
      "beta_access": false,
      "use_alt_dns": true
    }
  }
}
